metroscore/__init__.py
metroscore/analysis.py
metroscore/point_selection.py
metroscore/py.typed
metroscore/service_areas.py
metroscore/version.py
metroscore-0.2.0.dist-info/LICENSE
metroscore-0.2.0.dist-info/METADATA
metroscore-0.2.0.dist-info/WHEEL
metroscore-0.2.0.dist-info/top_level.txt
metroscore-0.2.0.dist-info/RECORD
